gastrodon/__init__.py
gastrodon/domain/__init__.py
gastrodon-1.0.0.dist-info/LICENSE.md
gastrodon-1.0.0.dist-info/METADATA
gastrodon-1.0.0.dist-info/WHEEL
gastrodon-1.0.0.dist-info/top_level.txt
gastrodon-1.0.0.dist-info/RECORD
