Metadata-Version: 2.1
Name: gastrodon
Version: 1.0.0
Summary: Toolkit to display,  analyze,  and visualize data and documents based on RDF graphs and the SPARQL query language using Pandas,  Jupyter, and other Python ecosystem tools.
Home-page: https://github.com/paulhoule/gastrodon
Author: Paul Houle
Author-email: paul.houle@ontology2.com
License: MIT
Keywords: sparql rdf rdflib pandas visualization
Platform: UNKNOWN
Classifier: Development Status :: 5 - Production/Stable
Classifier: Intended Audience :: Developers
Classifier: Intended Audience :: Science/Research
Classifier: Intended Audience :: Financial and Insurance Industry
Classifier: Intended Audience :: Healthcare Industry
Classifier: Intended Audience :: Information Technology
Classifier: Topic :: Database :: Front-Ends
Classifier: Topic :: Documentation :: Sphinx
Classifier: Topic :: Multimedia :: Graphics
Classifier: Topic :: Scientific/Engineering :: Information Analysis
Classifier: Topic :: Scientific/Engineering :: Visualization
Classifier: Topic :: Software Development :: Libraries :: Python Modules
Classifier: Topic :: Text Processing :: Markup :: HTML
Classifier: License :: OSI Approved :: MIT License
Classifier: Programming Language :: Python :: 3.7
Requires-Python: >=3.7
License-File: LICENSE.md
Requires-Dist: rdflib
Requires-Dist: pyparsing
Requires-Dist: IPython
Requires-Dist: SPARQLWrapper
Requires-Dist: uritools
Requires-Dist: pandas
Requires-Dist: ipython-autotime
Requires-Dist: matplotlib
Requires-Dist: bs4
Requires-Dist: sphinx
Requires-Dist: html5lib
